pyfs_bot/__init__.py
pyfs_bot/bot.py
pyfs_bot-1.0.0.dist-info/METADATA
pyfs_bot-1.0.0.dist-info/WHEEL
pyfs_bot-1.0.0.dist-info/top_level.txt
pyfs_bot-1.0.0.dist-info/RECORD
